pravah/__init__.py
pravah/main.py
pravah-0.1.7.dist-info/LICENSE
pravah-0.1.7.dist-info/METADATA
pravah-0.1.7.dist-info/WHEEL
pravah-0.1.7.dist-info/top_level.txt
pravah-0.1.7.dist-info/RECORD
