Metadata-Version: 2.1
Name: pravah
Version: 0.1.7
Summary: Data access layer
Home-page: https://github.com/pravahio
Author: Abhishek Upperwal
Author-email: mesh@soket.in
License: UNKNOWN
Platform: UNKNOWN
Classifier: Programming Language :: Python :: 3
Classifier: License :: OSI Approved :: MIT License
Classifier: Operating System :: OS Independent
Requires-Dist: mesh-rpc (>=0.1.6)
Requires-Dist: pravah-protocols
Requires-Dist: dlake (>=0.1.2)
